{
  "en": [
    {
      "name": "STIKOM Bali",
      "nameEn": "STIKOM Bali",
      "location": "Bali, Indonesia",
      "logo": "/uni/stikom-bali.webp",
      "specialty": "Computer & Information Technology"
    },
    {
      "name": "UIN Jakarta",
      "nameEn": "Universitas Islam Negeri Syarif Hidayatullah Jakarta",
      "location": "Jakarta, Indonesia",
      "logo": "/uni/uin-jakarta.jpg",
      "specialty": "Islamic Comprehensive University"
    },
    {
      "name": "UPI",
      "nameEn": "Universitas Pendidikan Indonesia",
      "location": "Bandung, Indonesia",
      "logo": "/uni/upi.png",
      "specialty": "Education & Engineering"
    },
    {
      "name": "UNLA Bandung",
      "nameEn": "Universitas Langlangbuana Bandung",
      "location": "Bandung, Indonesia",
      "logo": "/uni/unla-bandung.png",
      "specialty": "Comprehensive University"
    },
    {
      "name": "UI FMIPA",
      "nameEn": "Universitas Indonesia - FMIPA",
      "location": "Jakarta, Indonesia",
      "logo": "/uni/ui-fmipa.png",
      "specialty": "Mathematics & Natural Sciences"
    },
    {
      "name": "ITS",
      "nameEn": "Institut Teknologi Sepuluh Nopember",
      "location": "Surabaya, Indonesia",
      "logo": "/uni/its.png",
      "specialty": "Engineering & Technology"
    },
    {
      "name": "UNEJ",
      "nameEn": "Universitas Jember",
      "location": "Jember, Indonesia",
      "logo": "/uni/unej.webp",
      "specialty": "Comprehensive University"
    }
  ],
  "ja": [
    {
      "name": "STIKOM Bali",
      "nameEn": "STIKOM Bali",
      "location": "バリ, インドネシア",
      "logo": "/uni/stikom-bali.webp",
      "specialty": "コンピューター・情報技術"
    },
    {
      "name": "UIN Jakarta",
      "nameEn": "Universitas Islam Negeri Syarif Hidayatullah Jakarta",
      "location": "ジャカルタ, インドネシア", 
      "logo": "/uni/uin-jakarta.jpg",
      "specialty": "イスラム総合大学"
    },
    {
      "name": "UPI",
      "nameEn": "Universitas Pendidikan Indonesia",
      "location": "バンドン, インドネシア",
      "logo": "/uni/upi.png",
      "specialty": "教育・工学"
    },
    {
      "name": "UNLA Bandung",
      "nameEn": "Universitas Langlangbuana Bandung",
      "location": "バンドン, インドネシア",
      "logo": "/uni/unla-bandung.png",
      "specialty": "総合大学"
    },
    {
      "name": "UI FMIPA",
      "nameEn": "Universitas Indonesia - FMIPA",
      "location": "ジャカルタ, インドネシア",
      "logo": "/uni/ui-fmipa.png",
      "specialty": "数学・自然科学"
    },
    {
      "name": "ITS",
      "nameEn": "Institut Teknologi Sepuluh Nopember",
      "location": "スラバヤ, インドネシア",
      "logo": "/uni/its.png",
      "specialty": "工学・技術"
    },
    {
      "name": "UNEJ",
      "nameEn": "Universitas Jember",
      "location": "ジャンベル, インドネシア",
      "logo": "/uni/unej.webp",
      "specialty": "総合大学"
    }
  ],
  "id": [
    {
      "name": "STIKOM Bali",
      "nameEn": "STIKOM Bali",
      "location": "Bali, Indonesia",
      "logo": "/uni/stikom-bali.webp",
      "specialty": "Komputer & Teknologi Informasi"
    },
    {
      "name": "UIN Jakarta",
      "nameEn": "Universitas Islam Negeri Syarif Hidayatullah Jakarta",
      "location": "Jakarta, Indonesia", 
      "logo": "/uni/uin-jakarta.jpg",
      "specialty": "Universitas Islam Komprehensif"
    },
    {
      "name": "UPI",
      "nameEn": "Universitas Pendidikan Indonesia",
      "location": "Bandung, Indonesia",
      "logo": "/uni/upi.png",
      "specialty": "Pendidikan & Teknik"
    },
    {
      "name": "UNLA Bandung",
      "nameEn": "Universitas Langlangbuana Bandung",
      "location": "Bandung, Indonesia",
      "logo": "/uni/unla-bandung.png",
      "specialty": "Universitas Komprehensif"
    },
    {
      "name": "UI FMIPA",
      "nameEn": "Universitas Indonesia - FMIPA",
      "location": "Jakarta, Indonesia",
      "logo": "/uni/ui-fmipa.png",
      "specialty": "Matematika & Ilmu Pengetahuan Alam"
    },
    {
      "name": "ITS",
      "nameEn": "Institut Teknologi Sepuluh Nopember",
      "location": "Surabaya, Indonesia",
      "logo": "/uni/its.png",
      "specialty": "Teknik & Teknologi"
    },
    {
      "name": "UNEJ",
      "nameEn": "Universitas Jember",
      "location": "Jember, Indonesia",
      "logo": "/uni/unej.webp",
      "specialty": "Universitas Komprehensif"
    }
  ]
}